Verilog/Processor/ALU.v
/*
ALU module: two 32-bit operands + 4-bit control → 32-bit result + zero flag.

ALU Control | Operation
--------------------------
  0000       AND
  0001       OR
  0010       ADD
  0011       SLL  (shift left logical)
  0100       SUB
  0101       SRL  (shift right logical)
  0110       SRA  (shift right arithmetic)
  0111       XOR
  1000       SLT  (signed less-than)
  1001       SLTU (unsigned less-than)
*/

module ALU (
    input  [31:0] in1,
    input  [31:0] in2,
    input  [3:0]  alu_control,
    output reg [31:0] alu_result,
    output reg        zero_flag
);

    always @(*) begin
        case (alu_control)
            4'b0000: alu_result = in1 & in2;
            4'b0001: alu_result = in1 | in2;
            4'b0010: alu_result = in1 + in2;
            4'b0011: alu_result = in1 << in2[4:0];
            4'b0100: alu_result = in1 - in2;
            4'b0101: alu_result = in1 >> in2[4:0];
            4'b0110: alu_result = $signed(in1) >>> in2[4:0];
            4'b0111: alu_result = in1 ^ in2;
            4'b1000: alu_result = ($signed(in1) < $signed(in2)) ? 32'd1 : 32'd0;
            4'b1001: alu_result = (in1 < in2)                   ? 32'd1 : 32'd0;
            default: alu_result = 32'hx;
        endcase

        zero_flag = (alu_result == 32'd0) ? 1'b1 : 1'b0;
    end

endmodule

Verilog/ALU/ALU_tb.v
`include "ALU.v"

module stimulus ();
    reg  [31:0] A, B;
    reg  [3:0]  ALUControl;
    wire [31:0] ALUResult;
    wire        ZERO;

    ALU ALU_module (
        .in1(A), .in2(B),
        .alu_control(ALUControl),
        .alu_result(ALUResult),
        .zero_flag(ZERO)
    );

    initial begin
        $dumpfile("alu_output_wave.vcd");
        $dumpvars(0, stimulus);
    end

    initial
        $monitor($time, "\nA=%0d B=%0d ctrl=%b → result=%0d zero=%b\n",
                 A, B, ALUControl, ALUResult, ZERO);

    initial begin
                A = 15;  B = 9;   ALUControl = 4'b0010; // ADD  → 24
        #20     A = 15;  B = 9;   ALUControl = 4'b0100; // SUB  → 6
        #20     A = 15;  B = 9;   ALUControl = 4'b0000; // AND  → 9
        #20     A = 15;  B = 9;   ALUControl = 4'b0001; // OR   → 15
        #20     A = 15;  B = 9;   ALUControl = 4'b0111; // XOR  → 6
        #20     A = 1;   B = 3;   ALUControl = 4'b0011; // SLL  → 8
        #20     A = 16;  B = 2;   ALUControl = 4'b0101; // SRL  → 4
        #20     A = -8;  B = 2;   ALUControl = 4'b0110; // SRA  → -2
        #20     A = 5;   B = 10;  ALUControl = 4'b1000; // SLT  → 1
        #20     A = 10;  B = 5;   ALUControl = 4'b1000; // SLT  → 0
        #20     A = 5;   B = 5;   ALUControl = 4'b0100; // SUB  → 0 (zero flag)
    end

    initial #250 $finish;
endmodule

Verilog/ALU/alu_output_wave.vcd
$date
	Fri Mar 20 04:05:34 2026
$end
$version
	Icarus Verilog
$end
$timescale
	1s
$end
$scope module stimulus $end
$var wire 1 ! ZERO $end
$var wire 32 " ALUResult [31:0] $end
$var reg 32 # A [31:0] $end
$var reg 4 $ ALUControl [3:0] $end
$var reg 32 % B [31:0] $end
$scope module ALU_module $end
$var wire 4 & alu_control [3:0] $end
$var wire 32 ' in1 [31:0] $end
$var wire 32 ( in2 [31:0] $end
$var reg 32 ) alu_result [31:0] $end
$var reg 1 ! zero_flag $end
$upscope $end
$upscope $end
$enddefinitions $end
$comment Show the parameter values. $end
$dumpall
$end
#0
$dumpvars
b11000 )
b1001 (
b1111 '
b10 &
b1001 %
b10 $
b1111 #
b11000 "
0!
$end
#20
b110 "
b110 )
b100 $
b100 &
#40
b1001 "
b1001 )
b0 $
b0 &
#60
b1111 "
b1111 )
b1 $
b1 &
#80
b110 "
b110 )
b111 $
b111 &
#100
b1000 "
b1000 )
b11 $
b11 &
b11 %
b11 (
b1 #
b1 '
#120
b100 "
b100 )
b101 $
b101 &
b10 %
b10 (
b10000 #
b10000 '
#140
b11111111111111111111111111111110 "
b11111111111111111111111111111110 )
b110 $
b110 &
b11111111111111111111111111111000 #
b11111111111111111111111111111000 '
#160
b1 "
b1 )
b1000 $
b1000 &
b1010 %
b1010 (
b101 #
b101 '
#180
1!
b0 "
b0 )
b101 %
b101 (
b1010 #
b1010 '
#200
b100 $
b100 &
b101 #
b101 '
